wtools/__init__.py
wtools/bdist.py
wtools/box.py
wtools/depends.py
wtools/eclipse_make.py
wtools/eclipse_waf.py
wtools/indent.py
wtools/make.py
wtools/pkg.py
wtools/recurse.py
wtools/tree.py
wtools/util.py
wtools/waf.py
wtools/wcc.py
wtools/wmake.py
wtools/data/bdist-recipe.schema.json
wtools/data/pkg-platform.schema.json
wtools/data/pkg-recipe.schema.json
wtools-1.0.13.dist-info/LICENSE
wtools-1.0.13.dist-info/METADATA
wtools-1.0.13.dist-info/WHEEL
wtools-1.0.13.dist-info/entry_points.txt
wtools-1.0.13.dist-info/top_level.txt
wtools-1.0.13.dist-info/RECORD
