Metadata-Version: 2.1
Name: wtools
Version: 1.0.13
Summary: WAF build tools
Home-page: https://bitbucket.org/Moo7/wtools
Author: Michel Mooij
Author-email: michel.mooij7@gmail.com
Maintainer: Michel Mooij
Maintainer-email: michel.mooij7@gmail.com
License: MIT
Download-URL: https://bitbucket.org/Moo7/wtools/downloads/wtools-1.0.13.tar.gz
Keywords: waf,c,c++,eclipse,make,.rpm,.deb,.ipk,ipkg
Platform: any
Classifier: Development Status :: 4 - Beta
Classifier: Environment :: Console
Classifier: Intended Audience :: Developers
Classifier: License :: OSI Approved :: MIT License
Classifier: Operating System :: Microsoft :: Windows :: Windows 10
Classifier: Operating System :: Microsoft :: Windows :: Windows 7
Classifier: Operating System :: POSIX :: Linux
Classifier: Programming Language :: C
Classifier: Programming Language :: C++
Classifier: Programming Language :: Python :: 3.5
Classifier: Topic :: Software Development :: Build Tools
Classifier: Topic :: Software Development :: Embedded Systems
Classifier: Topic :: Utilities
Requires-Dist: distro
Requires-Dist: jsonschema (>=3.2.0)
Requires-Dist: python-magic (>=0.4.18)
Requires-Dist: wheel
